{
  "version": 1,
  "from_half": "structured",
  "to_half": "loop",
  "written_at": "2026-05-01T06:11:28.179404+00:00",
  "session_id": "sess_806f69c91167",
  "reason": "normalisation failed: missing venue_id",
  "context": "normalisation failed: missing venue_id",
  "data": {
    "task": "The structured half rejected the previous proposal. Reason: normalisation failed: missing venue_id. Produce an alternative.",
    "context": {
      "prior_result": {
        "subgoal_id": "sg_1",
        "assigned_half": "structured",
        "executor_results": []
      },
      "rejection_reason": "normalisation failed: missing venue_id",
      "retry": true
    }
  },
  "return_instructions": "Use the rejection reason to produce an alternative venue proposal, then hand off to structured again.",
  "constraints_reminder": null
}